pytest_psqlgraph/__init__.py
pytest_psqlgraph/helpers.py
pytest_psqlgraph/models.py
pytest_psqlgraph/plugin.py
pytest_psqlgraph/typings.py
pytest_psqlgraph-0.1.1.dist-info/LICENSE
pytest_psqlgraph-0.1.1.dist-info/METADATA
pytest_psqlgraph-0.1.1.dist-info/WHEEL
pytest_psqlgraph-0.1.1.dist-info/entry_points.txt
pytest_psqlgraph-0.1.1.dist-info/top_level.txt
pytest_psqlgraph-0.1.1.dist-info/zip-safe
pytest_psqlgraph-0.1.1.dist-info/RECORD
